[
  {
    "propertyCategory": "Residential",
    "propertyType": "House",
    "listingType": "sale",
    "title": "4 Bedroom House for sale in Sector 92, Gurgaon",
    "description": "",
    "state": "Haryana",
    "city": "Gurgaon",
    "locality": "Sector 92",
    "pincode": "",
    "bedrooms": 4,
    "bathrooms": 4,
    "furnishing": "",
    "floor": "",
    "area": 475,
    "areaUnit": "sqft",
    "price": 43500000,
    "selectedAmenities": [
      "East Facing",
      "Private Garden"
    ]
  },
  {
    "propertyCategory": "Residential",
    "propertyType": "House",
    "listingType": "sale",
    "title": "4 Bedroom House for sale in Sector 92, Gurgaon",
    "description": "",
    "state": "Haryana",
    "city": "Gurgaon",
    "locality": "Sector 92",
    "pincode": "",
    "bedrooms": 4,
    "bathrooms": 4,
    "furnishing": "",
    "floor": "",
    "area": 0,
    "areaUnit": "sqft",
    "price": 40000000,
    "selectedAmenities": [
      "North-East Facing",
      "Private Garden"
    ]
  },
  {
    "propertyCategory": "Residential",
    "propertyType": "House",
    "listingType": "sale",
    "title": "4 Bedroom House for sale in Sector 92, Gurgaon",
    "description": "",
    "state": "Haryana",
    "city": "Gurgaon",
    "locality": "Sector 92",
    "pincode": "",
    "bedrooms": 4,
    "bathrooms": 2,
    "furnishing": "",
    "floor": "",
    "area": 0,
    "areaUnit": "sqft",
    "price": 42000000,
    "selectedAmenities": [
      "East Facing",
      "Private Garden"
    ]
  },
  {
    "propertyCategory": "Residential",
    "propertyType": "House",
    "listingType": "sale",
    "title": "4 Bedroom House for sale in Sector 92, Gurgaon",
    "description": "",
    "state": "Haryana",
    "city": "Gurgaon",
    "locality": "Sector 92",
    "pincode": "",
    "bedrooms": 4,
    "bathrooms": 4,
    "furnishing": "",
    "floor": "",
    "area": 250,
    "areaUnit": "sqft",
    "price": 26500000,
    "selectedAmenities": [
      "North-East Facing",
      "DPS  Nearby"
    ]
  },
  {
    "propertyCategory": "Residential",
    "propertyType": "House",
    "listingType": "sale",
    "title": "4 Bedroom House for sale in Sector 92, Gurgaon",
    "description": "",
    "state": "Haryana",
    "city": "Gurgaon",
    "locality": "Sector 92",
    "pincode": "",
    "bedrooms": 4,
    "bathrooms": 4,
    "furnishing": "",
    "floor": "",
    "area": 0,
    "areaUnit": "sqft",
    "price": 43000000,
    "selectedAmenities": [
      "East Facing",
      "Private Garden"
    ]
  },
  {
    "propertyCategory": "Residential",
    "propertyType": "House",
    "listingType": "sale",
    "title": "4 Bedroom House for sale in Sector 92, Gurgaon",
    "description": "",
    "state": "Haryana",
    "city": "Gurgaon",
    "locality": "Sector 92",
    "pincode": "",
    "bedrooms": 4,
    "bathrooms": 4,
    "furnishing": "",
    "floor": "",
    "area": 475,
    "areaUnit": "sqft",
    "price": 43500000,
    "selectedAmenities": [
      "Private Garden",
      "Yaduvanshi school Nearby"
    ]
  },
  {
    "propertyCategory": "Residential",
    "propertyType": "House",
    "listingType": "sale",
    "title": "4 Bedroom House for sale in Sector 92, Gurgaon",
    "description": "",
    "state": "Haryana",
    "city": "Gurgaon",
    "locality": "Sector 92",
    "pincode": "",
    "bedrooms": 4,
    "bathrooms": 4,
    "furnishing": "",
    "floor": "",
    "area": 547,
    "areaUnit": "sqft",
    "price": 28000000,
    "selectedAmenities": [
      "Newly Constructed",
      "Recently Renovated"
    ]
  },
  {
    "propertyCategory": "Residential",
    "propertyType": "House",
    "listingType": "sale",
    "title": "4 Bedroom House for sale in Sector 92, Gurgaon",
    "description": "",
    "state": "Haryana",
    "city": "Gurgaon",
    "locality": "Sector 92",
    "pincode": "",
    "bedrooms": 4,
    "bathrooms": 4,
    "furnishing": "",
    "floor": "",
    "area": 700,
    "areaUnit": "sqft",
    "price": 31500000,
    "selectedAmenities": [
      "North-East Facing",
      "Sri Chaitanya school  Nearby"
    ]
  },
  {
    "propertyCategory": "Residential",
    "propertyType": "House",
    "listingType": "sale",
    "title": "4 Bedroom House for sale in Sector 92, Gurgaon",
    "description": "",
    "state": "Haryana",
    "city": "Gurgaon",
    "locality": "Sector 92",
    "pincode": "",
    "bedrooms": 4,
    "bathrooms": 4,
    "furnishing": "",
    "floor": "",
    "area": 700,
    "areaUnit": "sqft",
    "price": 40000000,
    "selectedAmenities": [
      "East Facing",
      "Overlooking Park/Garden"
    ]
  },
  {
    "propertyCategory": "Residential",
    "propertyType": "House",
    "listingType": "sale",
    "title": "5 Bedroom House for sale in Sector 92, Gurgaon",
    "description": "",
    "state": "Haryana",
    "city": "Gurgaon",
    "locality": "Sector 92",
    "pincode": "",
    "bedrooms": 5,
    "bathrooms": 4,
    "furnishing": "",
    "floor": "",
    "area": 0,
    "areaUnit": "sqft",
    "price": 45500000,
    "selectedAmenities": [
      "East Facing",
      "Private Garden"
    ]
  },
  {
    "propertyCategory": "Residential",
    "propertyType": "House",
    "listingType": "sale",
    "title": "4 Bedroom House for sale in Sector 92, Gurgaon",
    "description": "",
    "state": "Haryana",
    "city": "Gurgaon",
    "locality": "Sector 92",
    "pincode": "",
    "bedrooms": 4,
    "bathrooms": 4,
    "furnishing": "",
    "floor": "",
    "area": 520,
    "areaUnit": "sqft",
    "price": 40000000,
    "selectedAmenities": []
  },
  {
    "propertyCategory": "Residential",
    "propertyType": "House",
    "listingType": "sale",
    "title": "2 Bedroom House for sale in Sector 92, Gurgaon",
    "description": "",
    "state": "Haryana",
    "city": "Gurgaon",
    "locality": "Sector 92",
    "pincode": "",
    "bedrooms": 2,
    "bathrooms": 1,
    "furnishing": "",
    "floor": "",
    "area": 936,
    "areaUnit": "sqft",
    "price": 48,
    "selectedAmenities": []
  },
  {
    "propertyCategory": "Residential",
    "propertyType": "House",
    "listingType": "sale",
    "title": "2 BHK House for sale in Sector 92, Gurgaon",
    "description": "",
    "state": "Haryana",
    "city": "Gurgaon",
    "locality": "Sector 92",
    "pincode": "",
    "bedrooms": 2,
    "bathrooms": 2,
    "furnishing": "",
    "floor": "",
    "area": 320,
    "areaUnit": "sqft",
    "price": 93,
    "selectedAmenities": []
  },
  {
    "propertyCategory": "Residential",
    "propertyType": "House",
    "listingType": "sale",
    "title": "3 BHK House for sale in Sector 92, Gurgaon",
    "description": "",
    "state": "Haryana",
    "city": "Gurgaon",
    "locality": "Sector 92",
    "pincode": "",
    "bedrooms": 3,
    "bathrooms": 2,
    "furnishing": "",
    "floor": "",
    "area": 50,
    "areaUnit": "sqft",
    "price": 90,
    "selectedAmenities": []
  },
  {
    "propertyCategory": "Residential",
    "propertyType": "House",
    "listingType": "sale",
    "title": "2 BHK House for sale in Sector 92, Gurgaon",
    "description": "",
    "state": "Haryana",
    "city": "Gurgaon",
    "locality": "Sector 92",
    "pincode": "",
    "bedrooms": 2,
    "bathrooms": 2,
    "furnishing": "",
    "floor": "",
    "area": 320,
    "areaUnit": "sqft",
    "price": 80,
    "selectedAmenities": [
      "East Facing",
      "Newly Constructed"
    ]
  },
  {
    "propertyCategory": "Residential",
    "propertyType": "House",
    "listingType": "sale",
    "title": "3 BHK House for sale in Sector 92, Gurgaon",
    "description": "",
    "state": "Haryana",
    "city": "Gurgaon",
    "locality": "Sector 92",
    "pincode": "",
    "bedrooms": 3,
    "bathrooms": 2,
    "furnishing": "",
    "floor": "",
    "area": 714,
    "areaUnit": "sqft",
    "price": 80,
    "selectedAmenities": []
  },
  {
    "propertyCategory": "Residential",
    "propertyType": "House",
    "listingType": "sale",
    "title": "3 BHK House for sale in Sector 92, Gurgaon",
    "description": "",
    "state": "Haryana",
    "city": "Gurgaon",
    "locality": "Sector 92",
    "pincode": "",
    "bedrooms": 3,
    "bathrooms": 3,
    "furnishing": "",
    "floor": "",
    "area": 720,
    "areaUnit": "sqft",
    "price": 80,
    "selectedAmenities": []
  },
  {
    "propertyCategory": "Residential",
    "propertyType": "House",
    "listingType": "sale",
    "title": "3 BHK House for sale in Sector 92, Gurgaon",
    "description": "",
    "state": "Haryana",
    "city": "Gurgaon",
    "locality": "Sector 92",
    "pincode": "",
    "bedrooms": 3,
    "bathrooms": 3,
    "furnishing": "",
    "floor": "",
    "area": 900,
    "areaUnit": "sqft",
    "price": 80,
    "selectedAmenities": []
  },
  {
    "propertyCategory": "Residential",
    "propertyType": "House",
    "listingType": "sale",
    "title": "3 BHK House for sale in Sector 92, Gurgaon",
    "description": "",
    "state": "Haryana",
    "city": "Gurgaon",
    "locality": "Sector 92",
    "pincode": "",
    "bedrooms": 3,
    "bathrooms": 2,
    "furnishing": "",
    "floor": "",
    "area": 693,
    "areaUnit": "sqft",
    "price": 81,
    "selectedAmenities": [
      "North-East Facing",
      "Rao Bharat Singh International within 500m"
    ]
  },
  {
    "propertyCategory": "Residential",
    "propertyType": "House",
    "listingType": "sale",
    "title": "3 BHK House for sale in Sector 92, Gurgaon",
    "description": "",
    "state": "Haryana",
    "city": "Gurgaon",
    "locality": "Sector 92",
    "pincode": "",
    "bedrooms": 3,
    "bathrooms": 2,
    "furnishing": "",
    "floor": "",
    "area": 90,
    "areaUnit": "sqft",
    "price": 832,
    "selectedAmenities": [
      "North-East Facing",
      "Private Garden"
    ]
  },
  {
    "propertyCategory": "Residential",
    "propertyType": "House",
    "listingType": "sale",
    "title": "2 BHK House for sale in Sector 92, Gurgaon",
    "description": "",
    "state": "Haryana",
    "city": "Gurgaon",
    "locality": "Sector 92",
    "pincode": "",
    "bedrooms": 2,
    "bathrooms": 2,
    "furnishing": "",
    "floor": "",
    "area": 960,
    "areaUnit": "sqft",
    "price": 832,
    "selectedAmenities": [
      "North-East Facing",
      "Gated Society"
    ]
  },
  {
    "propertyCategory": "Residential",
    "propertyType": "House",
    "listingType": "sale",
    "title": "3 BHK House for sale in Sector 92, Gurgaon",
    "description": "",
    "state": "Haryana",
    "city": "Gurgaon",
    "locality": "Sector 92",
    "pincode": "",
    "bedrooms": 3,
    "bathrooms": 2,
    "furnishing": "",
    "floor": "",
    "area": 190,
    "areaUnit": "sqft",
    "price": 98,
    "selectedAmenities": [
      "North-East Facing",
      "Private Garden"
    ]
  },
  {
    "propertyCategory": "Residential",
    "propertyType": "House",
    "listingType": "sale",
    "title": "2 BHK House for sale in Sector 92, Gurgaon",
    "description": "",
    "state": "Haryana",
    "city": "Gurgaon",
    "locality": "Sector 92",
    "pincode": "",
    "bedrooms": 2,
    "bathrooms": 2,
    "furnishing": "",
    "floor": "",
    "area": 960,
    "areaUnit": "sqft",
    "price": 854,
    "selectedAmenities": [
      "North-East Facing",
      "Top Floor"
    ]
  },
  {
    "propertyCategory": "Residential",
    "propertyType": "House",
    "listingType": "sale",
    "title": "3 BHK House for sale in Sector 92, Gurgaon",
    "description": "",
    "state": "Haryana",
    "city": "Gurgaon",
    "locality": "Sector 92",
    "pincode": "",
    "bedrooms": 3,
    "bathrooms": 2,
    "furnishing": "",
    "floor": "",
    "area": 190,
    "areaUnit": "sqft",
    "price": 843,
    "selectedAmenities": [
      "North-East Facing",
      "Private Garden"
    ]
  },
  {
    "propertyCategory": "Residential",
    "propertyType": "House",
    "listingType": "sale",
    "title": "3 BHK House for sale in Sector 92, Gurgaon",
    "description": "",
    "state": "Haryana",
    "city": "Gurgaon",
    "locality": "Sector 92",
    "pincode": "",
    "bedrooms": 3,
    "bathrooms": 2,
    "furnishing": "",
    "floor": "",
    "area": 90,
    "areaUnit": "sqft",
    "price": 97,
    "selectedAmenities": [
      "North-East Facing",
      "Gated Society"
    ]
  },
  {
    "propertyCategory": "Residential",
    "propertyType": "House",
    "listingType": "sale",
    "title": "3 BHK House for sale in Sector 92, Gurgaon",
    "description": "",
    "state": "Haryana",
    "city": "Gurgaon",
    "locality": "Sector 92",
    "pincode": "",
    "bedrooms": 3,
    "bathrooms": 2,
    "furnishing": "",
    "floor": "",
    "area": 90,
    "areaUnit": "sqft",
    "price": 987,
    "selectedAmenities": [
      "North-East Facing",
      "Gated Society"
    ]
  },
  {
    "propertyCategory": "Residential",
    "propertyType": "House",
    "listingType": "rent",
    "title": "2 BHK House for sale in Sector 92, Gurgaon",
    "description": "",
    "state": "Haryana",
    "city": "Gurgaon",
    "locality": "Sector 92",
    "pincode": "",
    "bedrooms": 2,
    "bathrooms": 2,
    "furnishing": "",
    "floor": "",
    "area": 0,
    "areaUnit": "sqft",
    "price": 97,
    "selectedAmenities": []
  },
  {
    "propertyCategory": "Residential",
    "propertyType": "House",
    "listingType": "sale",
    "title": "2 BHK House for sale in Sector 92, Gurgaon",
    "description": "",
    "state": "Haryana",
    "city": "Gurgaon",
    "locality": "Sector 92",
    "pincode": "",
    "bedrooms": 2,
    "bathrooms": 2,
    "furnishing": "",
    "floor": "",
    "area": 0,
    "areaUnit": "sqft",
    "price": 100,
    "selectedAmenities": [
      "North-East Facing",
      "Gated Society"
    ]
  },
  {
    "propertyCategory": "Residential",
    "propertyType": "House",
    "listingType": "sale",
    "title": "2 BHK House for sale in Sector 92, Gurgaon",
    "description": "",
    "state": "Haryana",
    "city": "Gurgaon",
    "locality": "Sector 92",
    "pincode": "",
    "bedrooms": 2,
    "bathrooms": 2,
    "furnishing": "",
    "floor": "",
    "area": 980,
    "areaUnit": "sqft",
    "price": 98,
    "selectedAmenities": [
      "Fitness Center/ Gym",
      "Club house"
    ]
  },
  {
    "propertyCategory": "Residential",
    "propertyType": "House",
    "listingType": "sale",
    "title": "2 BHK House for sale in Sector 92, Gurgaon",
    "description": "",
    "state": "Haryana",
    "city": "Gurgaon",
    "locality": "Sector 92",
    "pincode": "",
    "bedrooms": 2,
    "bathrooms": 2,
    "furnishing": "",
    "floor": "",
    "area": 80,
    "areaUnit": "sqft",
    "price": 98,
    "selectedAmenities": [
      "North-East Facing",
      "Recently Renovated"
    ]
  }
]