[
  {
    "propertyCategory": "Residential",
    "propertyType": "House",
    "listingType": "lease",
    "title": "6 Bedroom House for sale in Sushant Lok Phase 1, Gurgaon",
    "description": "",
    "state": "Haryana",
    "city": "Gurgaon",
    "locality": "Sushant Lok Phase 1",
    "pincode": "",
    "bedrooms": 6,
    "bathrooms": 6,
    "furnishing": "",
    "floor": "",
    "area": 935,
    "areaUnit": "sqft",
    "price": 65100000,
    "selectedAmenities": []
  },
  {
    "propertyCategory": "Residential",
    "propertyType": "House",
    "listingType": "sale",
    "title": "9 Bedroom House for sale in Sushant Lok Phase 1, Gurgaon",
    "description": "",
    "state": "Haryana",
    "city": "Gurgaon",
    "locality": "Sushant Lok Phase 1",
    "pincode": "",
    "bedrooms": 9,
    "bathrooms": 8,
    "furnishing": "",
    "floor": "",
    "area": 0,
    "areaUnit": "sqft",
    "price": 120000000,
    "selectedAmenities": [
      "North-East Facing"
    ]
  },
  {
    "propertyCategory": "Residential",
    "propertyType": "House",
    "listingType": "sale",
    "title": "12 Bedroom House for sale in Block C, Sushant Lok Phase 1, Gurgaon",
    "description": "",
    "state": "Haryana",
    "city": "Gurgaon",
    "locality": "Sushant Lok Phase 1",
    "pincode": "",
    "bedrooms": 12,
    "bathrooms": 13,
    "furnishing": "",
    "floor": "",
    "area": 762,
    "areaUnit": "sqft",
    "price": 179000000,
    "selectedAmenities": [
      "North Facing",
      "Private Garden"
    ]
  },
  {
    "propertyCategory": "Residential",
    "propertyType": "House",
    "listingType": "rent",
    "title": "11 Bedroom House for sale in Block C, Sushant Lok Phase 1, Gurgaon",
    "description": "",
    "state": "Haryana",
    "city": "Gurgaon",
    "locality": "Sushant Lok Phase 1",
    "pincode": "",
    "bedrooms": 11,
    "bathrooms": 11,
    "furnishing": "",
    "floor": "",
    "area": 675,
    "areaUnit": "sqft",
    "price": 52500000,
    "selectedAmenities": []
  },
  {
    "propertyCategory": "Residential",
    "propertyType": "House",
    "listingType": "rent",
    "title": "11 Bedroom House for sale in Block C, Sushant Lok Phase 1, Gurgaon",
    "description": "",
    "state": "Haryana",
    "city": "Gurgaon",
    "locality": "Sushant Lok Phase 1",
    "pincode": "",
    "bedrooms": 11,
    "bathrooms": 11,
    "furnishing": "",
    "floor": "",
    "area": 549,
    "areaUnit": "sqft",
    "price": 35000000,
    "selectedAmenities": [
      "North-East Facing",
      "Huda City within 1km"
    ]
  },
  {
    "propertyCategory": "Residential",
    "propertyType": "House",
    "listingType": "sale",
    "title": "10 Bedroom House for sale in B Block Sushant Lok Phase 1, Gurgaon",
    "description": "",
    "state": "Haryana",
    "city": "Gurgaon",
    "locality": "Sushant Lok Phase 1",
    "pincode": "",
    "bedrooms": 10,
    "bathrooms": 10,
    "furnishing": "",
    "floor": "",
    "area": 700,
    "areaUnit": "sqft",
    "price": 107500000,
    "selectedAmenities": [
      "North Facing",
      "HUDA City Metro Nearby"
    ]
  },
  {
    "propertyCategory": "Residential",
    "propertyType": "House",
    "listingType": "rent",
    "title": "5 Bedroom House for sale in Block C, Sushant Lok Phase 1, Gurgaon",
    "description": "",
    "state": "Haryana",
    "city": "Gurgaon",
    "locality": "Sushant Lok Phase 1",
    "pincode": "",
    "bedrooms": 5,
    "bathrooms": 6,
    "furnishing": "",
    "floor": "",
    "area": 935,
    "areaUnit": "sqft",
    "price": 95000000,
    "selectedAmenities": [
      "Huda City Metro Nearby",
      "DPS School Nearby"
    ]
  },
  {
    "propertyCategory": "Residential",
    "propertyType": "House",
    "listingType": "rent",
    "title": "10 Bedroom House for sale in Block C, Sushant Lok Phase 1, Gurgaon",
    "description": "",
    "state": "Haryana",
    "city": "Gurgaon",
    "locality": "Sushant Lok Phase 1",
    "pincode": "",
    "bedrooms": 10,
    "bathrooms": 10,
    "furnishing": "",
    "floor": "",
    "area": 762,
    "areaUnit": "sqft",
    "price": 130000000,
    "selectedAmenities": [
      "HUDA City Metro Nearby",
      "DPS School Nearby"
    ]
  },
  {
    "propertyCategory": "Residential",
    "propertyType": "House",
    "listingType": "sale",
    "title": "10 Bedroom House for sale in B Block Sushant Lok Phase 1, Gurgaon",
    "description": "",
    "state": "Haryana",
    "city": "Gurgaon",
    "locality": "Sushant Lok Phase 1",
    "pincode": "",
    "bedrooms": 10,
    "bathrooms": 10,
    "furnishing": "",
    "floor": "",
    "area": 700,
    "areaUnit": "sqft",
    "price": 106000000,
    "selectedAmenities": []
  },
  {
    "propertyCategory": "Residential",
    "propertyType": "House",
    "listingType": "sale",
    "title": "3 Bedroom House for sale in Sushant Lok Phase 1, Gurgaon",
    "description": "",
    "state": "Haryana",
    "city": "Gurgaon",
    "locality": "Sushant Lok Phase 1",
    "pincode": "",
    "bedrooms": 3,
    "bathrooms": 3,
    "furnishing": "",
    "floor": "",
    "area": 771,
    "areaUnit": "sqft",
    "price": 140000000,
    "selectedAmenities": []
  },
  {
    "propertyCategory": "Residential",
    "propertyType": "House",
    "listingType": "sale",
    "title": "4 Bedroom House for sale in Sushant Lok Phase 1, Gurgaon",
    "description": "",
    "state": "Haryana",
    "city": "Gurgaon",
    "locality": "Sushant Lok Phase 1",
    "pincode": "",
    "bedrooms": 4,
    "bathrooms": 6,
    "furnishing": "",
    "floor": "",
    "area": 512,
    "areaUnit": "sqft",
    "price": 99000000,
    "selectedAmenities": []
  },
  {
    "propertyCategory": "Residential",
    "propertyType": "House",
    "listingType": "sale",
    "title": "4 Bedroom House for sale in Sushant Lok Phase 1, Gurgaon",
    "description": "",
    "state": "Haryana",
    "city": "Gurgaon",
    "locality": "Sushant Lok Phase 1",
    "pincode": "",
    "bedrooms": 4,
    "bathrooms": 4,
    "furnishing": "",
    "floor": "",
    "area": 350,
    "areaUnit": "sqft",
    "price": 62500000,
    "selectedAmenities": []
  },
  {
    "propertyCategory": "Residential",
    "propertyType": "House",
    "listingType": "rent",
    "title": "11 Bedroom House for sale in Block C, Sushant Lok Phase 1, Gurgaon",
    "description": "",
    "state": "Haryana",
    "city": "Gurgaon",
    "locality": "Sushant Lok Phase 1",
    "pincode": "",
    "bedrooms": 11,
    "bathrooms": 11,
    "furnishing": "",
    "floor": "",
    "area": 594,
    "areaUnit": "sqft",
    "price": 35000000,
    "selectedAmenities": []
  },
  {
    "propertyCategory": "Residential",
    "propertyType": "House",
    "listingType": "rent",
    "title": "22 Bedroom House for sale in Sushant Lok Phase 1, Gurgaon",
    "description": "",
    "state": "Haryana",
    "city": "Gurgaon",
    "locality": "Sushant Lok Phase 1",
    "pincode": "",
    "bedrooms": 22,
    "bathrooms": 22,
    "furnishing": "",
    "floor": "",
    "area": 215,
    "areaUnit": "sqft",
    "price": 90000000,
    "selectedAmenities": []
  },
  {
    "propertyCategory": "Residential",
    "propertyType": "House",
    "listingType": "rent",
    "title": "10 Bedroom House for sale in Sushant Lok Phase 1, Gurgaon",
    "description": "",
    "state": "Haryana",
    "city": "Gurgaon",
    "locality": "Sushant Lok Phase 1",
    "pincode": "",
    "bedrooms": 10,
    "bathrooms": 10,
    "furnishing": "",
    "floor": "",
    "area": 200,
    "areaUnit": "sqft",
    "price": 180000000,
    "selectedAmenities": []
  },
  {
    "propertyCategory": "Residential",
    "propertyType": "House",
    "listingType": "sale",
    "title": "9 Bedroom House for sale in Sushant Lok Phase 1, Gurgaon",
    "description": "",
    "state": "Haryana",
    "city": "Gurgaon",
    "locality": "Sushant Lok Phase 1",
    "pincode": "",
    "bedrooms": 9,
    "bathrooms": 10,
    "furnishing": "",
    "floor": "",
    "area": 492,
    "areaUnit": "sqft",
    "price": 130000000,
    "selectedAmenities": [
      "North Facing",
      "Private Garden"
    ]
  },
  {
    "propertyCategory": "Residential",
    "propertyType": "House",
    "listingType": "sale",
    "title": "9 Bedroom House for sale in Sushant Lok Phase 1, Gurgaon",
    "description": "",
    "state": "Haryana",
    "city": "Gurgaon",
    "locality": "Sushant Lok Phase 1",
    "pincode": "",
    "bedrooms": 9,
    "bathrooms": 9,
    "furnishing": "",
    "floor": "",
    "area": 762,
    "areaUnit": "sqft",
    "price": 158900000,
    "selectedAmenities": [
      "Private Garden",
      "Gated Society"
    ]
  },
  {
    "propertyCategory": "Residential",
    "propertyType": "House",
    "listingType": "sale",
    "title": "5 Bedroom House for sale in Block C, Sushant Lok Phase 1, Gurgaon",
    "description": "",
    "state": "Haryana",
    "city": "Gurgaon",
    "locality": "Sushant Lok Phase 1",
    "pincode": "",
    "bedrooms": 5,
    "bathrooms": 5,
    "furnishing": "",
    "floor": "",
    "area": 935,
    "areaUnit": "sqft",
    "price": 92500000,
    "selectedAmenities": [
      "Private Garden",
      "Huda metro station within 500m"
    ]
  },
  {
    "propertyCategory": "Residential",
    "propertyType": "House",
    "listingType": "sale",
    "title": "3 Bedroom House for sale in Sushant Lok Phase 1, Gurgaon",
    "description": "",
    "state": "Haryana",
    "city": "Gurgaon",
    "locality": "Sushant Lok Phase 1",
    "pincode": "",
    "bedrooms": 3,
    "bathrooms": 3,
    "furnishing": "",
    "floor": "",
    "area": 650,
    "areaUnit": "sqft",
    "price": 27000000,
    "selectedAmenities": [
      "Gated Society",
      "Marble Flooring"
    ]
  },
  {
    "propertyCategory": "Residential",
    "propertyType": "House",
    "listingType": "sale",
    "title": "5 Bedroom House for sale in Sushant Lok Phase 1, Gurgaon",
    "description": "",
    "state": "Haryana",
    "city": "Gurgaon",
    "locality": "Sushant Lok Phase 1",
    "pincode": "",
    "bedrooms": 5,
    "bathrooms": 6,
    "furnishing": "",
    "floor": "",
    "area": 0,
    "areaUnit": "sqft",
    "price": 107500000,
    "selectedAmenities": []
  },
  {
    "propertyCategory": "Residential",
    "propertyType": "House",
    "listingType": "rent",
    "title": "10 Bedroom House for sale in Block C, Sushant Lok Phase 1, Gurgaon",
    "description": "",
    "state": "Haryana",
    "city": "Gurgaon",
    "locality": "Sushant Lok Phase 1",
    "pincode": "",
    "bedrooms": 10,
    "bathrooms": 10,
    "furnishing": "",
    "floor": "",
    "area": 560,
    "areaUnit": "sqft",
    "price": 47000000,
    "selectedAmenities": [
      "Private Garden",
      "Millanium city centre  Nearby"
    ]
  },
  {
    "propertyCategory": "Residential",
    "propertyType": "House",
    "listingType": "rent",
    "title": "10 Bedroom House for sale in Block C, Sushant Lok Phase 1, Gurgaon",
    "description": "",
    "state": "Haryana",
    "city": "Gurgaon",
    "locality": "Sushant Lok Phase 1",
    "pincode": "",
    "bedrooms": 10,
    "bathrooms": 10,
    "furnishing": "",
    "floor": "",
    "area": 594,
    "areaUnit": "sqft",
    "price": 33500000,
    "selectedAmenities": [
      "Huda Metro within 1km",
      "DPS, Sushant LoK-1 within 500m"
    ]
  },
  {
    "propertyCategory": "Residential",
    "propertyType": "House",
    "listingType": "sale",
    "title": "6 Bedroom House for sale in Sushant Lok Phase 1, Gurgaon",
    "description": "",
    "state": "Haryana",
    "city": "Gurgaon",
    "locality": "Sushant Lok Phase 1",
    "pincode": "",
    "bedrooms": 6,
    "bathrooms": 6,
    "furnishing": "",
    "floor": "",
    "area": 317,
    "areaUnit": "sqft",
    "price": 420000000,
    "selectedAmenities": [
      "North-East Facing",
      "Private Garden"
    ]
  },
  {
    "propertyCategory": "Residential",
    "propertyType": "House",
    "listingType": "sale",
    "title": "6 Bedroom House in Sushant Lok Phase 1, Gurgaon",
    "description": "",
    "state": "Haryana",
    "city": "Gurgaon",
    "locality": "Sushant Lok Phase 1",
    "pincode": "",
    "bedrooms": 6,
    "bathrooms": 6,
    "furnishing": "",
    "floor": "",
    "area": 317,
    "areaUnit": "sqft",
    "price": 420000000,
    "selectedAmenities": [
      "North-East Facing",
      "Private Garden"
    ]
  },
  {
    "propertyCategory": "Residential",
    "propertyType": "House",
    "listingType": "sale",
    "title": "9 Bedroom House in Sushant Lok Phase 1, Gurgaon",
    "description": "",
    "state": "Haryana",
    "city": "Gurgaon",
    "locality": "Sushant Lok Phase 1",
    "pincode": "",
    "bedrooms": 9,
    "bathrooms": 9,
    "furnishing": "",
    "floor": "",
    "area": 762,
    "areaUnit": "sqft",
    "price": 181500000,
    "selectedAmenities": [
      "North Facing",
      "Gated Society"
    ]
  },
  {
    "propertyCategory": "Residential",
    "propertyType": "House",
    "listingType": "sale",
    "title": "3 Bedroom House in Sushant Lok Phase 1, Gurgaon",
    "description": "",
    "state": "Haryana",
    "city": "Gurgaon",
    "locality": "Sushant Lok Phase 1",
    "pincode": "",
    "bedrooms": 3,
    "bathrooms": 3,
    "furnishing": "",
    "floor": "",
    "area": 771,
    "areaUnit": "sqft",
    "price": 125000000,
    "selectedAmenities": [
      "North-East Facing",
      "Sector 55,56 Metro Station Nearby"
    ]
  },
  {
    "propertyCategory": "Residential",
    "propertyType": "House",
    "listingType": "sale",
    "title": "5 Bedroom House in Block C, Sushant Lok Phase 1, Gurgaon",
    "description": "",
    "state": "Haryana",
    "city": "Gurgaon",
    "locality": "Sushant Lok Phase 1",
    "pincode": "",
    "bedrooms": 5,
    "bathrooms": 5,
    "furnishing": "",
    "floor": "",
    "area": 935,
    "areaUnit": "sqft",
    "price": 85000000,
    "selectedAmenities": [
      "North-East Facing",
      "Gated Society"
    ]
  },
  {
    "propertyCategory": "Residential",
    "propertyType": "House",
    "listingType": "sale",
    "title": "2 Bedroom House in Sushant Lok Phase 1, Gurgaon",
    "description": "",
    "state": "Haryana",
    "city": "Gurgaon",
    "locality": "Sushant Lok Phase 1",
    "pincode": "",
    "bedrooms": 2,
    "bathrooms": 2,
    "furnishing": "",
    "floor": "",
    "area": 935,
    "areaUnit": "sqft",
    "price": 95000000,
    "selectedAmenities": [
      "North-East Facing",
      "Gated Society"
    ]
  },
  {
    "propertyCategory": "Residential",
    "propertyType": "House",
    "listingType": "sale",
    "title": "16 Bedroom House in Block C, Sushant Lok Phase 1, Gurgaon",
    "description": "",
    "state": "Haryana",
    "city": "Gurgaon",
    "locality": "Sushant Lok Phase 1",
    "pincode": "",
    "bedrooms": 16,
    "bathrooms": 16,
    "furnishing": "",
    "floor": "",
    "area": 618,
    "areaUnit": "sqft",
    "price": 180000000,
    "selectedAmenities": [
      "North-East Facing",
      "Private Garden"
    ]
  },
  {
    "propertyCategory": "Residential",
    "propertyType": "House",
    "listingType": "sale",
    "title": "6 Bedroom House in Sushant Lok Phase 1, Gurgaon",
    "description": "",
    "state": "Haryana",
    "city": "Gurgaon",
    "locality": "Sushant Lok Phase 1",
    "pincode": "",
    "bedrooms": 6,
    "bathrooms": 5,
    "furnishing": "",
    "floor": "",
    "area": 935,
    "areaUnit": "sqft",
    "price": 84500000,
    "selectedAmenities": [
      "East Facing",
      "Private Garden"
    ]
  }
]