[
  {
    "propertyCategory": "Residential",
    "propertyType": "Builder Floor",
    "listingType": "sale",
    "title": "4 BHK Independent Builder Floor in Sector 50, Gurgaon",
    "description": "",
    "state": "Haryana",
    "city": "Gurgaon",
    "locality": "Sector 50",
    "pincode": "",
    "bedrooms": 4,
    "bathrooms": 4,
    "furnishing": "",
    "floor": "",
    "area": 518,
    "areaUnit": "sqft",
    "price": 58000000,
    "selectedAmenities": [
      "2nd out of 4 Floors",
      "Lift"
    ]
  },
  {
    "propertyCategory": "Residential",
    "propertyType": "Builder Floor",
    "listingType": "sale",
    "title": "5 BHK Independent Builder Floor in Sector 50, Gurgaon",
    "description": "",
    "state": "Haryana",
    "city": "Gurgaon",
    "locality": "Sector 50",
    "pincode": "",
    "bedrooms": 5,
    "bathrooms": 6,
    "furnishing": "",
    "floor": "",
    "area": 500,
    "areaUnit": "sqft",
    "price": 66500000,
    "selectedAmenities": [
      "2nd out of 4 Floors",
      "Lift"
    ]
  },
  {
    "propertyCategory": "Residential",
    "propertyType": "Apartment",
    "listingType": "sale",
    "title": "4 BHK Flat in Sector 50, Gurgaon",
    "description": "",
    "state": "Haryana",
    "city": "Gurgaon",
    "locality": "Sector 50",
    "pincode": "",
    "bedrooms": 4,
    "bathrooms": 4,
    "furnishing": "",
    "floor": "",
    "area": 200,
    "areaUnit": "sqft",
    "price": 42500000,
    "selectedAmenities": [
      "Gated Society",
      "Corner Property"
    ]
  },
  {
    "propertyCategory": "Residential",
    "propertyType": "Plot",
    "listingType": "sale",
    "title": "Residential land / Plot in Sector 50, Gurgaon",
    "description": "",
    "state": "Haryana",
    "city": "Gurgaon",
    "locality": "Sector 50",
    "pincode": "",
    "bedrooms": 0,
    "bathrooms": 0,
    "furnishing": "",
    "floor": "",
    "area": 421,
    "areaUnit": "sqft",
    "price": 92800000,
    "selectedAmenities": [
      "ARTMIS HOSPITAL  within 1km",
      "Overlooking Main Road"
    ]
  },
  {
    "propertyCategory": "Residential",
    "propertyType": "Builder Floor",
    "listingType": "sale",
    "title": "4 BHK Independent Builder Floor in Nirvana Country, Gurgaon",
    "description": "",
    "state": "Haryana",
    "city": "Gurgaon",
    "locality": "Sector 50",
    "pincode": "",
    "bedrooms": 4,
    "bathrooms": 4,
    "furnishing": "",
    "floor": "",
    "area": 0,
    "areaUnit": "sqft",
    "price": 62500000,
    "selectedAmenities": [
      "1st out of 4 Floors",
      "Lift"
    ]
  },
  {
    "propertyCategory": "Residential",
    "propertyType": "Builder Floor",
    "listingType": "sale",
    "title": "4 BHK Independent Builder Floor in Nirvana Country, Gurgaon",
    "description": "",
    "state": "Haryana",
    "city": "Gurgaon",
    "locality": "Sector 50",
    "pincode": "",
    "bedrooms": 4,
    "bathrooms": 4,
    "furnishing": "",
    "floor": "",
    "area": 700,
    "areaUnit": "sqft",
    "price": 58900000,
    "selectedAmenities": [
      "2nd out of 4 Floors",
      "Lift"
    ]
  },
  {
    "propertyCategory": "Residential",
    "propertyType": "Builder Floor",
    "listingType": "sale",
    "title": "4 BHK Independent Builder Floor in Sector 50, Gurgaon",
    "description": "",
    "state": "Haryana",
    "city": "Gurgaon",
    "locality": "Sector 50",
    "pincode": "",
    "bedrooms": 4,
    "bathrooms": 4,
    "furnishing": "",
    "floor": "",
    "area": 500,
    "areaUnit": "sqft",
    "price": 32000000,
    "selectedAmenities": [
      "2nd out of 4 Floors"
    ]
  },
  {
    "propertyCategory": "Residential",
    "propertyType": "Builder Floor",
    "listingType": "sale",
    "title": "4 BHK Independent Builder Floor in Sector 50, Gurgaon",
    "description": "",
    "state": "Haryana",
    "city": "Gurgaon",
    "locality": "Sector 50",
    "pincode": "",
    "bedrooms": 4,
    "bathrooms": 4,
    "furnishing": "",
    "floor": "",
    "area": 900,
    "areaUnit": "sqft",
    "price": 37500000,
    "selectedAmenities": [
      "2nd out of 4 Floors",
      "Gated Society"
    ]
  },
  {
    "propertyCategory": "Residential",
    "propertyType": "Builder Floor",
    "listingType": "sale",
    "title": "3 BHK Independent Builder Floor in Sector 50, Gurgaon",
    "description": "",
    "state": "Haryana",
    "city": "Gurgaon",
    "locality": "Sector 50",
    "pincode": "",
    "bedrooms": 3,
    "bathrooms": 3,
    "furnishing": "",
    "floor": "",
    "area": 720,
    "areaUnit": "sqft",
    "price": 27500000,
    "selectedAmenities": [
      "3rd out of 4 Floors",
      "Huda CIty Centre  within 1.5km"
    ]
  },
  {
    "propertyCategory": "Residential",
    "propertyType": "Builder Floor",
    "listingType": "sale",
    "title": "3 BHK Independent Builder Floor in Sector 50, Gurgaon",
    "description": "",
    "state": "Haryana",
    "city": "Gurgaon",
    "locality": "Sector 50",
    "pincode": "",
    "bedrooms": 3,
    "bathrooms": 3,
    "furnishing": "",
    "floor": "",
    "area": 420,
    "areaUnit": "sqft",
    "price": 31500000,
    "selectedAmenities": [
      "2nd out of 4 Floors",
      "Huda City Centre  within 1.5km"
    ]
  }
]