[
  {
    "propertyCategory": "Residential",
    "propertyType": "Villa",
    "listingType": "rent",
    "title": "4 BHK Flat for rent in Charmwood Village, Faridabad",
    "description": "",
    "state": "Haryana",
    "city": "faridabad",
    "locality": "  Charmwood Village ",
    "pincode": "",
    "bedrooms": 4,
    "bathrooms": 4,
    "furnishing": "",
    "floor": 0,
    "area": 107,
    "areaUnit": "sqft",
    "price": 65000,
    "selectedAmenities": [
      "4 Baths",
      "North-East Facing"
    ]
  },
  {
    "propertyCategory": "Residential",
    "propertyType": "Villa",
    "listingType": "rent",
    "title": "2 BHK Flat for rent in Charmwood Village, Faridabad",
    "description": "",
    "state": "Haryana",
    "city": "faridabad",
    "locality": "  Charmwood Village ",
    "pincode": "",
    "bedrooms": 2,
    "bathrooms": 2,
    "furnishing": "",
    "floor": 0,
    "area": 827,
    "areaUnit": "sqft",
    "price": 19000,
    "selectedAmenities": [
      "2 Baths",
      "North-East Facing"
    ]
  },
  {
    "propertyCategory": "Residential",
    "propertyType": "Villa",
    "listingType": "rent",
    "title": "4 BHK Flat for rent in Charmwood Village, Faridabad",
    "description": "",
    "state": "Haryana",
    "city": "faridabad",
    "locality": "  Charmwood Village ",
    "pincode": "",
    "bedrooms": 4,
    "bathrooms": 4,
    "furnishing": "",
    "floor": 0,
    "area": 384,
    "areaUnit": "sqft",
    "price": 90000,
    "selectedAmenities": []
  },
  {
    "propertyCategory": "Residential",
    "propertyType": "Villa",
    "listingType": "rent",
    "title": "2 BHK Flat for rent in Charmwood Village, Faridabad",
    "description": "",
    "state": "Haryana",
    "city": "faridabad",
    "locality": "  Charmwood Village ",
    "pincode": "",
    "bedrooms": 2,
    "bathrooms": 2,
    "furnishing": "",
    "floor": 0,
    "area": 827,
    "areaUnit": "sqft",
    "price": 20000,
    "selectedAmenities": [
      "2 Baths",
      "Close to School"
    ]
  },
  {
    "propertyCategory": "Residential",
    "propertyType": "Villa",
    "listingType": "rent",
    "title": "3 BHK Flat for rent in Charmwood Village, Faridabad",
    "description": "",
    "state": "Haryana",
    "city": "faridabad",
    "locality": "  Charmwood Village ",
    "pincode": "",
    "bedrooms": 3,
    "bathrooms": 2,
    "furnishing": "",
    "floor": 0,
    "area": 330,
    "areaUnit": "sqft",
    "price": 45000,
    "selectedAmenities": [
      "Ground Floor",
      "Tughlakabad metro  Nearby"
    ]
  },
  {
    "propertyCategory": "Residential",
    "propertyType": "Villa",
    "listingType": "rent",
    "title": "2 BHK Flat for rent in Charmwood Village, Faridabad",
    "description": "",
    "state": "Haryana",
    "city": "faridabad",
    "locality": "  Charmwood Village ",
    "pincode": "",
    "bedrooms": 2,
    "bathrooms": 2,
    "furnishing": "",
    "floor": 0,
    "area": 950,
    "areaUnit": "sqft",
    "price": 25000,
    "selectedAmenities": []
  },
  {
    "propertyCategory": "Residential",
    "propertyType": "Villa",
    "listingType": "rent",
    "title": "2 BHK Flat for rent in Charmwood Village, Faridabad",
    "description": "",
    "state": "Haryana",
    "city": "faridabad",
    "locality": "  Charmwood Village ",
    "pincode": "",
    "bedrooms": 2,
    "bathrooms": 2,
    "furnishing": "",
    "floor": 0,
    "area": 950,
    "areaUnit": "sqft",
    "price": 23000,
    "selectedAmenities": [
      "2 Baths",
      "Close to Metro Station"
    ]
  },
  {
    "propertyCategory": "Residential",
    "propertyType": "Villa",
    "listingType": "rent",
    "title": "3 BHK Flat for rent in Charmwood Village, Faridabad",
    "description": "",
    "state": "Haryana",
    "city": "faridabad",
    "locality": "  Charmwood Village ",
    "pincode": "",
    "bedrooms": 3,
    "bathrooms": 2,
    "furnishing": "",
    "floor": 0,
    "area": 330,
    "areaUnit": "sqft",
    "price": 40000,
    "selectedAmenities": []
  },
  {
    "propertyCategory": "Residential",
    "propertyType": "Villa",
    "listingType": "rent",
    "title": "3 BHK Flat for rent in Charmwood Village, Faridabad",
    "description": "",
    "state": "Haryana",
    "city": "faridabad",
    "locality": "  Charmwood Village ",
    "pincode": "",
    "bedrooms": 3,
    "bathrooms": 2,
    "furnishing": "",
    "floor": 0,
    "area": 462,
    "areaUnit": "sqft",
    "price": 40000,
    "selectedAmenities": [
      "2 Baths",
      "Full Power Backup"
    ]
  },
  {
    "propertyCategory": "Residential",
    "propertyType": "Villa",
    "listingType": "rent",
    "title": "3 BHK Flat for rent in Charmwood Village, Faridabad",
    "description": "",
    "state": "Haryana",
    "city": "faridabad",
    "locality": "  Charmwood Village ",
    "pincode": "",
    "bedrooms": 3,
    "bathrooms": 2,
    "furnishing": "",
    "floor": 0,
    "area": 431,
    "areaUnit": "sqft",
    "price": 50000,
    "selectedAmenities": [
      "2 Baths",
      "East Facing"
    ]
  },
  {
    "propertyCategory": "Residential",
    "propertyType": "Villa",
    "listingType": "rent",
    "title": "3 BHK Flat for rent in Charmwood Village, Faridabad",
    "description": "",
    "state": "Haryana",
    "city": "faridabad",
    "locality": "  Charmwood Village ",
    "pincode": "",
    "bedrooms": 3,
    "bathrooms": 2,
    "furnishing": "",
    "floor": 0,
    "area": 462,
    "areaUnit": "sqft",
    "price": 45000,
    "selectedAmenities": [
      "2 Baths",
      "North-East Facing"
    ]
  },
  {
    "propertyCategory": "Residential",
    "propertyType": "Villa",
    "listingType": "rent",
    "title": "3 BHK Flat for rent in Charmwood Village, Faridabad",
    "description": "",
    "state": "Haryana",
    "city": "faridabad",
    "locality": "  Charmwood Village ",
    "pincode": "",
    "bedrooms": 3,
    "bathrooms": 2,
    "furnishing": "",
    "floor": 0,
    "area": 462,
    "areaUnit": "sqft",
    "price": 46000,
    "selectedAmenities": [
      "2 Baths",
      "Gated Society"
    ]
  },
  {
    "propertyCategory": "Residential",
    "propertyType": "Villa",
    "listingType": "rent",
    "title": "3 BHK Flat for rent in Charmwood Village, Faridabad",
    "description": "",
    "state": "Haryana",
    "city": "faridabad",
    "locality": "  Charmwood Village ",
    "pincode": "",
    "bedrooms": 3,
    "bathrooms": 2,
    "furnishing": "",
    "floor": 0,
    "area": 550,
    "areaUnit": "sqft",
    "price": 50000,
    "selectedAmenities": [
      "2 Baths",
      "Full Power Backup"
    ]
  },
  {
    "propertyCategory": "Residential",
    "propertyType": "Villa",
    "listingType": "rent",
    "title": "3 BHK Flat for rent in Charmwood Village, Faridabad",
    "description": "",
    "state": "Haryana",
    "city": "faridabad",
    "locality": "  Charmwood Village ",
    "pincode": "",
    "bedrooms": 3,
    "bathrooms": 2,
    "furnishing": "",
    "floor": 0,
    "area": 350,
    "areaUnit": "sqft",
    "price": 45000,
    "selectedAmenities": [
      "2 Baths",
      "Gated Society"
    ]
  },
  {
    "propertyCategory": "Residential",
    "propertyType": "Villa",
    "listingType": "rent",
    "title": "2 BHK Flat for rent in Charmwood Village, Faridabad",
    "description": "",
    "state": "Haryana",
    "city": "faridabad",
    "locality": "  Charmwood Village ",
    "pincode": "",
    "bedrooms": 2,
    "bathrooms": 2,
    "furnishing": "",
    "floor": 0,
    "area": 450,
    "areaUnit": "sqft",
    "price": 40000,
    "selectedAmenities": [
      "2 Baths",
      "Full Power Backup"
    ]
  },
  {
    "propertyCategory": "Residential",
    "propertyType": "Villa",
    "listingType": "rent",
    "title": "2 BHK Flat for rent in Charmwood Village, Faridabad",
    "description": "",
    "state": "Haryana",
    "city": "faridabad",
    "locality": "  Charmwood Village ",
    "pincode": "",
    "bedrooms": 2,
    "bathrooms": 2,
    "furnishing": "",
    "floor": 0,
    "area": 283,
    "areaUnit": "sqft",
    "price": 36500,
    "selectedAmenities": [
      "2 Baths",
      "Full Power Backup"
    ]
  },
  {
    "propertyCategory": "Residential",
    "propertyType": "House",
    "listingType": "rent",
    "title": "3 Bedroom House for rent in Charmwood Village, Faridabad",
    "description": "",
    "state": "Haryana",
    "city": "faridabad",
    "locality": "  Charmwood Village ",
    "pincode": "",
    "bedrooms": 3,
    "bathrooms": 2,
    "furnishing": "",
    "floor": 0,
    "area": 500,
    "areaUnit": "sqft",
    "price": 36000,
    "selectedAmenities": [
      "Tughlakabad metro Nearby",
      "Manav rachna school Nearby"
    ]
  },
  {
    "propertyCategory": "Residential",
    "propertyType": "Villa",
    "listingType": "rent",
    "title": "5 BHK Flat for rent in Charmwood Village, Faridabad",
    "description": "",
    "state": "Haryana",
    "city": "faridabad",
    "locality": "  Charmwood Village ",
    "pincode": "",
    "bedrooms": 5,
    "bathrooms": 6,
    "furnishing": "",
    "floor": 0,
    "area": 400,
    "areaUnit": "sqft",
    "price": 135,
    "selectedAmenities": [
      "6 Baths",
      "East Facing"
    ]
  },
  {
    "propertyCategory": "Residential",
    "propertyType": "Villa",
    "listingType": "rent",
    "title": "5 BHK Flat for rent in Charmwood Village, Faridabad",
    "description": "",
    "state": "Haryana",
    "city": "faridabad",
    "locality": "  Charmwood Village ",
    "pincode": "",
    "bedrooms": 5,
    "bathrooms": 5,
    "furnishing": "",
    "floor": 0,
    "area": 400,
    "areaUnit": "sqft",
    "price": 135,
    "selectedAmenities": [
      "Full Power Backup",
      "Tugulkabad metro Nearby"
    ]
  },
  {
    "propertyCategory": "Residential",
    "propertyType": "Villa",
    "listingType": "rent",
    "title": "2 BHK Flat for rent in Charmwood Village, Faridabad",
    "description": "",
    "state": "Haryana",
    "city": "faridabad",
    "locality": "  Charmwood Village ",
    "pincode": "",
    "bedrooms": 2,
    "bathrooms": 2,
    "furnishing": "",
    "floor": 0,
    "area": 950,
    "areaUnit": "sqft",
    "price": 31000,
    "selectedAmenities": [
      "Full Power Backup",
      "Tughlakabad metro  Nearby"
    ]
  },
  {
    "propertyCategory": "Residential",
    "propertyType": "Villa",
    "listingType": "rent",
    "title": "3 BHK Flat for rent in Charmwood Village, Faridabad",
    "description": "",
    "state": "Haryana",
    "city": "faridabad",
    "locality": "  Charmwood Village ",
    "pincode": "",
    "bedrooms": 3,
    "bathrooms": 3,
    "furnishing": "",
    "floor": 0,
    "area": 600,
    "areaUnit": "sqft",
    "price": 65000,
    "selectedAmenities": []
  },
  {
    "propertyCategory": "Residential",
    "propertyType": "Villa",
    "listingType": "rent",
    "title": "2 BHK Flat for rent in Charmwood Village, Faridabad",
    "description": "",
    "state": "Haryana",
    "city": "faridabad",
    "locality": "  Charmwood Village ",
    "pincode": "",
    "bedrooms": 2,
    "bathrooms": 2,
    "furnishing": "",
    "floor": 0,
    "area": 947,
    "areaUnit": "sqft",
    "price": 25000,
    "selectedAmenities": []
  },
  {
    "propertyCategory": "Residential",
    "propertyType": "Villa",
    "listingType": "rent",
    "title": "2 BHK Flat for rent in Charmwood Village, Faridabad",
    "description": "",
    "state": "Haryana",
    "city": "faridabad",
    "locality": "  Charmwood Village ",
    "pincode": "",
    "bedrooms": 2,
    "bathrooms": 2,
    "furnishing": "",
    "floor": 0,
    "area": 950,
    "areaUnit": "sqft",
    "price": 28000,
    "selectedAmenities": []
  },
  {
    "propertyCategory": "Residential",
    "propertyType": "Villa",
    "listingType": "rent",
    "title": "3 BHK Independent Builder Floor for rent in Charmwood Village, Faridabad",
    "description": "",
    "state": "Haryana",
    "city": "faridabad",
    "locality": "  Charmwood Village ",
    "pincode": "",
    "bedrooms": 3,
    "bathrooms": 2,
    "furnishing": "",
    "floor": 22,
    "area": 450,
    "areaUnit": "sqft",
    "price": 35000,
    "selectedAmenities": [
      "2nd out of 2 Floors",
      "Gated Society"
    ]
  },
  {
    "propertyCategory": "Residential",
    "propertyType": "Villa",
    "listingType": "rent",
    "title": "2 BHK Flat for rent in Charmwood Village, Faridabad",
    "description": "",
    "state": "Haryana",
    "city": "faridabad",
    "locality": "  Charmwood Village ",
    "pincode": "",
    "bedrooms": 2,
    "bathrooms": 2,
    "furnishing": "",
    "floor": 0,
    "area": 827,
    "areaUnit": "sqft",
    "price": 19000,
    "selectedAmenities": [
      "Tughlakabad  Nearby",
      "Manav rachna  Nearby"
    ]
  },
  {
    "propertyCategory": "Residential",
    "propertyType": "Villa",
    "listingType": "rent",
    "title": "2 BHK Flat for rent in Charmwood Village, Faridabad",
    "description": "",
    "state": "Haryana",
    "city": "faridabad",
    "locality": "  Charmwood Village ",
    "pincode": "",
    "bedrooms": 2,
    "bathrooms": 2,
    "furnishing": "",
    "floor": 0,
    "area": 283,
    "areaUnit": "sqft",
    "price": 35000,
    "selectedAmenities": []
  },
  {
    "propertyCategory": "Residential",
    "propertyType": "Villa",
    "listingType": "rent",
    "title": "4 BHK Flat for rent in Charmwood Village, Faridabad",
    "description": "",
    "state": "Haryana",
    "city": "faridabad",
    "locality": "  Charmwood Village ",
    "pincode": "",
    "bedrooms": 4,
    "bathrooms": 4,
    "furnishing": "",
    "floor": 0,
    "area": 107,
    "areaUnit": "sqft",
    "price": 50000,
    "selectedAmenities": [
      "4 Baths",
      "North Facing"
    ]
  },
  {
    "propertyCategory": "Residential",
    "propertyType": "Villa",
    "listingType": "rent",
    "title": "3 BHK Independent Builder Floor for rent in Charmwood Village, Faridabad",
    "description": "",
    "state": "Haryana",
    "city": "faridabad",
    "locality": "  Charmwood Village ",
    "pincode": "",
    "bedrooms": 3,
    "bathrooms": 2,
    "furnishing": "",
    "floor": 13,
    "area": 500,
    "areaUnit": "sqft",
    "price": 35000,
    "selectedAmenities": [
      "1st out of 3 Floors",
      "Gated Society"
    ]
  },
  {
    "propertyCategory": "Residential",
    "propertyType": "Villa",
    "listingType": "rent",
    "title": "3 BHK Independent Builder Floor for rent in Charmwood Village, Faridabad",
    "description": "",
    "state": "Haryana",
    "city": "faridabad",
    "locality": "  Charmwood Village ",
    "pincode": "",
    "bedrooms": 3,
    "bathrooms": 2,
    "furnishing": "",
    "floor": 13,
    "area": 500,
    "areaUnit": "sqft",
    "price": 35000,
    "selectedAmenities": [
      "1st out of 3 Floors",
      "Gated Society"
    ]
  },
  {
    "propertyCategory": "Residential",
    "propertyType": "House",
    "listingType": "rent",
    "title": "4 BHK Independent Builder Floor for rent in Charmwood Village, Faridabad",
    "description": "",
    "state": "Haryana",
    "city": "faridabad",
    "locality": "  Charmwood Village ",
    "pincode": "",
    "bedrooms": 4,
    "bathrooms": 5,
    "furnishing": "",
    "floor": 13,
    "area": 520,
    "areaUnit": "sqft",
    "price": 55000,
    "selectedAmenities": [
      "1st out of 3 Floors",
      "Corner Property"
    ]
  }
]