[
  {
    "propertyCategory": "Residential",
    "propertyType": "Builder Floor",
    "listingType": "rent",
    "title": "4 BHK Independent Builder Floor for rent in Sector 17",
    "description": "",
    "state": "Haryana",
    "city": "faridabad",
    "locality": "Sector 17",
    "pincode": "",
    "bedrooms": 4,
    "bathrooms": 4,
    "furnishing": "Furnished",
    "floor": 3,
    "area": 3150,
    "areaUnit": "sqft",
    "price": 55000,
    "selectedAmenities": []
  },
  {
    "propertyCategory": "Residential",
    "propertyType": "Builder Floor",
    "listingType": "rent",
    "title": "2 BHK Independent Builder Floor for rent in Sector 17",
    "description": "",
    "state": "Haryana",
    "city": "faridabad",
    "locality": "Sector 17",
    "pincode": "",
    "bedrooms": 2,
    "bathrooms": 2,
    "furnishing": "Furnished",
    "floor": 1,
    "area": 2250,
    "areaUnit": "sqft",
    "price": 24000,
    "selectedAmenities": []
  },
  {
    "propertyCategory": "Residential",
    "propertyType": "Builder Floor",
    "listingType": "rent",
    "title": "3 BHK Independent Builder Floor for rent in Sector 17",
    "description": "",
    "state": "Haryana",
    "city": "faridabad",
    "locality": "Sector 17",
    "pincode": "",
    "bedrooms": 3,
    "bathrooms": 3,
    "furnishing": "Furnished",
    "floor": 2,
    "area": 1900,
    "areaUnit": "sqft",
    "price": 30000,
    "selectedAmenities": [
      "Amenities:",
      "Pool",
      "Gym",
      "Lift",
      "Parking"
    ]
  },
  {
    "propertyCategory": "Residential",
    "propertyType": "Builder Floor",
    "listingType": "rent",
    "title": "3 BHK Independent Builder Floor for rent in Sector 17",
    "description": "",
    "state": "Haryana",
    "city": "faridabad",
    "locality": "Sector 17",
    "pincode": "",
    "bedrooms": 3,
    "bathrooms": 3,
    "furnishing": "Furnished",
    "floor": 2,
    "area": 1900,
    "areaUnit": "sqft",
    "price": 25000,
    "selectedAmenities": []
  },
  {
    "propertyCategory": "Residential",
    "propertyType": "Builder Floor",
    "listingType": "rent",
    "title": "2 BHK Independent Builder Floor for rent in Sector 17",
    "description": "",
    "state": "Haryana",
    "city": "faridabad",
    "locality": "Sector 17",
    "pincode": "",
    "bedrooms": 2,
    "bathrooms": 2,
    "furnishing": "Furnished",
    "floor": 2,
    "area": 2500,
    "areaUnit": "sqft",
    "price": 25000,
    "selectedAmenities": []
  },
  {
    "propertyCategory": "Residential",
    "propertyType": "Builder Floor",
    "listingType": "rent",
    "title": "2 BHK Independent House for rent in Sector 17",
    "description": "",
    "state": "Haryana",
    "city": "faridabad",
    "locality": "Sector 17",
    "pincode": "",
    "bedrooms": 2,
    "bathrooms": 2,
    "furnishing": "Furnished",
    "floor": 0,
    "area": 1400,
    "areaUnit": "sqft",
    "price": 20000,
    "selectedAmenities": []
  },
  {
    "propertyCategory": "Residential",
    "propertyType": "Builder Floor",
    "listingType": "rent",
    "title": "1 RK Studio for rent in Sector 17",
    "description": "",
    "state": "Haryana",
    "city": "faridabad",
    "locality": "Sector 17",
    "pincode": "",
    "bedrooms": 0,
    "bathrooms": 1,
    "furnishing": "Furnished",
    "floor": 1,
    "area": 300,
    "areaUnit": "sqft",
    "price": 12000,
    "selectedAmenities": []
  },
  {
    "propertyCategory": "Residential",
    "propertyType": "Builder Floor",
    "listingType": "rent",
    "title": "4 BHK Independent Builder Floor for rent in Sector 17",
    "description": "",
    "state": "Haryana",
    "city": "faridabad",
    "locality": "Sector 17",
    "pincode": "",
    "bedrooms": 4,
    "bathrooms": 4,
    "furnishing": "Furnished",
    "floor": 3,
    "area": 3000,
    "areaUnit": "sqft",
    "price": 50000,
    "selectedAmenities": []
  },
  {
    "propertyCategory": "Residential",
    "propertyType": "Builder Floor",
    "listingType": "rent",
    "title": "3 BHK Flat for rent in Sector 17",
    "description": "",
    "state": "Haryana",
    "city": "faridabad",
    "locality": "Sector 17",
    "pincode": "",
    "bedrooms": 3,
    "bathrooms": 3,
    "furnishing": "Furnished",
    "floor": 0,
    "area": 1575,
    "areaUnit": "sqft",
    "price": 25000,
    "selectedAmenities": []
  },
  {
    "propertyCategory": "Residential",
    "propertyType": "Builder Floor",
    "listingType": "rent",
    "title": "1 RK Independent House for rent in Sector 17",
    "description": "",
    "state": "Haryana",
    "city": "faridabad",
    "locality": "Sector 17",
    "pincode": "",
    "bedrooms": 0,
    "bathrooms": 1,
    "furnishing": "Furnished",
    "floor": 0,
    "area": 250,
    "areaUnit": "sqft",
    "price": 3500,
    "selectedAmenities": []
  },
  {
    "propertyCategory": "Residential",
    "propertyType": "Builder Floor",
    "listingType": "rent",
    "title": "3 BHK Independent Builder Floor for rent in Sector 17",
    "description": "",
    "state": "Haryana",
    "city": "faridabad",
    "locality": "Sector 17",
    "pincode": "",
    "bedrooms": 3,
    "bathrooms": 4,
    "furnishing": "Furnished",
    "floor": 2,
    "area": 3150,
    "areaUnit": "sqft",
    "price": 75000,
    "selectedAmenities": [
      "Amenities:",
      "Pool",
      "Gym",
      "Lift",
      "Parking"
    ]
  },
  {
    "propertyCategory": "Residential",
    "propertyType": "Builder Floor",
    "listingType": "rent",
    "title": "4.5 BHK Independent Builder Floor for rent in Sector 17",
    "description": "",
    "state": "Haryana",
    "city": "faridabad",
    "locality": "Sector 17",
    "pincode": "",
    "bedrooms": 5,
    "bathrooms": 4,
    "furnishing": "Furnished",
    "floor": 2,
    "area": 3600,
    "areaUnit": "sqft",
    "price": 90000,
    "selectedAmenities": []
  }
]